compass/__init__.py
compass/ast/__init__.py
compass/ast/assign.py
compass/ast/await_statement.py
compass/ast/declaration.py
compass/ast/each.py
compass/ast/emit_statement.py
compass/ast/expression.py
compass/ast/extern.py
compass/ast/if_statement.py
compass/ast/input_declaration.py
compass/ast/local_statement.py
compass/ast/module.py
compass/ast/node.py
compass/ast/number.py
compass/ast/output_declaration.py
compass/ast/par.py
compass/ast/seq.py
compass/ast/signal.py
compass/ast/signal_expression.py
compass/ast/statement.py
compass/ast/submodule.py
compass/ast/tree.py
compass/ast/binary/__init__.py
compass/ast/binary/and_op.py
compass/ast/binary/binary.py
compass/ast/binary/bitand_op.py
compass/ast/binary/bitor_op.py
compass/ast/binary/div_op.py
compass/ast/binary/highereq_op.py
compass/ast/binary/higherneq_op.py
compass/ast/binary/lowereq_op.py
compass/ast/binary/lowerneq_op.py
compass/ast/binary/lshift_op.py
compass/ast/binary/minus_op.py
compass/ast/binary/mod_op.py
compass/ast/binary/noteq_op.py
compass/ast/binary/or_op.py
compass/ast/binary/plus_op.py
compass/ast/binary/rshift_op.py
compass/ast/binary/testeq_op.py
compass/ast/binary/times_op.py
compass/ast/binary/xor_op.py
compass/ast/unary/__init__.py
compass/ast/unary/complement_op.py
compass/ast/unary/not_op.py
compass/ast/unary/uminus_op.py
compass/ast/unary/unary.py
compass/codegen/c/__init__.py
compass/codegen/c/declaration.py
compass/codegen/c/expression.py
compass/codegen/c/module.py
compass/codegen/c/statement.py
compass/codegen/c/tree.py
compass/codegen/compass/__init__.py
compass/codegen/compass/declaration.py
compass/codegen/compass/expression.py
compass/codegen/compass/module.py
compass/codegen/compass/statement.py
compass/codegen/compass/tree.py
compass/codegen/debug/__init__.py
compass/codegen/debug/tree.py
compass/codegen/header/__init__.py
compass/codegen/header/module.py
compass/codegen/header/tree.py
compass/codegen/utils/__init__.py
compass/codegen/utils/inner_context.py
roadelou_compass-0.0.8.dist-info/LICENSE
roadelou_compass-0.0.8.dist-info/METADATA
roadelou_compass-0.0.8.dist-info/WHEEL
roadelou_compass-0.0.8.dist-info/entry_points.txt
roadelou_compass-0.0.8.dist-info/top_level.txt
roadelou_compass-0.0.8.dist-info/RECORD
