Metadata-Version: 2.1
Name: roadelou-compass
Version: 0.0.8
Summary: Simple synchronous programming language
Home-page: https://github.com/roadelou/compass
Author: roadelou
Author-email: 
License: GPL3
Platform: UNKNOWN
Classifier: License :: OSI Approved :: GNU General Public License v3 (GPLv3)
Classifier: Operating System :: POSIX :: Linux
Classifier: Topic :: Software Development :: Compilers
Classifier: Topic :: Software Development :: Code Generators
Classifier: Topic :: System :: Hardware
Requires-Python: >=3.6
Requires-Dist: sly
